{"supplier_id": "SUP001", "name": "New York Estate Sales", "contact_person": "David Webster", "email": "contact@newyorkestatesales.com", "phone": "+1-855-303-8055", "address": "{\"street\": \"1583 Heather Views Apt. 870\", \"city\": \"Paris\", \"country\": \"Belgium\"}", "specialty": "Accessoires Vintage", "lead_time_days": 17, "minimum_order": 1947, "payment_terms": "Net 30", "quality_rating": 4.8, "established_date": "2010-03-22", "is_active": true, "vintage_era_focus": "1950s-60s", "authentication_service": false, "certifications": "Certifi\u00e9 Maison"}
{"supplier_id": "SUP002", "name": "Maisons de Couture Parisiennes", "contact_person": "Harry Hall", "email": "contact@maisonsdecoutureparisiennes.com", "phone": "969.538.4032", "address": "{\"street\": \"532 Johnson Neck Suite 250\", \"city\": \"Florence\", \"country\": \"Italy\"}", "specialty": "Haute Couture Vintage", "lead_time_days": 34, "minimum_order": 1358, "payment_terms": "Virement imm\u00e9diat", "quality_rating": 4.2, "established_date": "2011-03-23", "is_active": true, "vintage_era_focus": "1970s-80s", "authentication_service": true, "certifications": "Certifi\u00e9 Maison"}
{"supplier_id": "SUP003", "name": "New York Estate Sales", "contact_person": "Alyssa Santos", "email": "contact@newyorkestatesales.com", "phone": "932.251.5193", "address": "{\"street\": \"6539 Jodi Plains Suite 869\", \"city\": \"New York\", \"country\": \"United Kingdom\"}", "specialty": "Accessoires Vintage", "lead_time_days": 39, "minimum_order": 677, "payment_terms": "Net 30", "quality_rating": 5.0, "established_date": "2007-04-30", "is_active": true, "vintage_era_focus": "1970s-80s", "authentication_service": true, "certifications": "Authentifi\u00e9 Vestiaire"}
{"supplier_id": "SUP004", "name": "Ateliers Vintage Milano", "contact_person": "Barbara Guzman", "email": "contact@ateliersvintagemilano.com", "phone": "408-450-3660x2471", "address": "{\"street\": \"45946 Gaines Springs Suite 696\", \"city\": \"London\", \"country\": \"Japan\"}", "specialty": "Pr\u00eat-\u00e0-Porter de Luxe", "lead_time_days": 16, "minimum_order": 1500, "payment_terms": "Net 45", "quality_rating": 4.5, "established_date": "2007-02-18", "is_active": false, "vintage_era_focus": "1990s-2000s", "authentication_service": true, "certifications": "Authentifi\u00e9 Vestiaire"}
{"supplier_id": "SUP005", "name": "London Vintage Collective", "contact_person": "Kristina Johnson", "email": "contact@londonvintagecollective.com", "phone": "(998)642-4197", "address": "{\"street\": \"982 Kelly Garden Apt. 818\", \"city\": \"Florence\", \"country\": \"Italy\"}", "specialty": "Haute Couture Vintage", "lead_time_days": 38, "minimum_order": 1615, "payment_terms": "Net 45", "quality_rating": 4.5, "established_date": "2013-09-03", "is_active": true, "vintage_era_focus": "Multi-\u00e9poque", "authentication_service": true, "certifications": "Authentifi\u00e9 Vestiaire"}
{"supplier_id": "SUP006", "name": "Maisons de Couture Parisiennes", "contact_person": "Crystal Hoover", "email": "contact@maisonsdecoutureparisiennes.com", "phone": "(510)377-9010", "address": "{\"street\": \"0374 Sandra Lakes Apt. 481\", \"city\": \"Milan\", \"country\": \"United States\"}", "specialty": "Pi\u00e8ces Rares Collection", "lead_time_days": 39, "minimum_order": 1502, "payment_terms": "Virement imm\u00e9diat", "quality_rating": 4.8, "established_date": "2007-08-15", "is_active": true, "vintage_era_focus": "Multi-\u00e9poque", "authentication_service": true, "certifications": "Certifi\u00e9 Maison"}
{"supplier_id": "SUP007", "name": "Maisons de Couture Parisiennes", "contact_person": "Ethan Mckay", "email": "contact@maisonsdecoutureparisiennes.com", "phone": "+1-789-277-1458x3682", "address": "{\"street\": \"1627 Michael Islands\", \"city\": \"Milan\", \"country\": \"Belgium\"}", "specialty": "Pi\u00e8ces Rares Collection", "lead_time_days": 9, "minimum_order": 1741, "payment_terms": "Net 45", "quality_rating": 4.5, "established_date": "2007-08-29", "is_active": true, "vintage_era_focus": "1950s-60s", "authentication_service": true, "certifications": "Expertise Ind\u00e9pendante"}
{"supplier_id": "SUP008", "name": "Archives Mode & Style", "contact_person": "John Smith", "email": "contact@archivesmode&style.com", "phone": "(225)240-9047x2022", "address": "{\"street\": \"743 Anthony Mount\", \"city\": \"Milan\", \"country\": \"France\"}", "specialty": "Haute Couture Vintage", "lead_time_days": 33, "minimum_order": 249, "payment_terms": "Net 30", "quality_rating": 5.0, "established_date": "2012-05-30", "is_active": true, "vintage_era_focus": "Multi-\u00e9poque", "authentication_service": true, "certifications": "Expertise Ind\u00e9pendante"}
{"supplier_id": "SUP009", "name": "Maisons de Couture Parisiennes", "contact_person": "Luis Byrd", "email": "contact@maisonsdecoutureparisiennes.com", "phone": "+1-978-545-2795", "address": "{\"street\": \"41397 Carla Mills\", \"city\": \"Milan\", \"country\": \"United States\"}", "specialty": "Pi\u00e8ces Rares Collection", "lead_time_days": 42, "minimum_order": 1117, "payment_terms": "Virement imm\u00e9diat", "quality_rating": 4.6, "established_date": "2017-03-12", "is_active": true, "vintage_era_focus": "1950s-60s", "authentication_service": true, "certifications": "Certifi\u00e9 Maison"}
{"supplier_id": "SUP010", "name": "Maisons de Couture Parisiennes", "contact_person": "Dr. Katrina Myers MD", "email": "contact@maisonsdecoutureparisiennes.com", "phone": "477-660-9794", "address": "{\"street\": \"618 Carey Parkways Suite 858\", \"city\": \"Tokyo\", \"country\": \"United Kingdom\"}", "specialty": "Pi\u00e8ces Rares Collection", "lead_time_days": 37, "minimum_order": 1468, "payment_terms": "Net 45", "quality_rating": 4.7, "established_date": "2001-11-18", "is_active": true, "vintage_era_focus": "Multi-\u00e9poque", "authentication_service": true, "certifications": "Expertise Ind\u00e9pendante"}
{"supplier_id": "SUP011", "name": "Archives Mode & Style", "contact_person": "Tammy Khan", "email": "contact@archivesmode&style.com", "phone": "588.616.0124x193", "address": "{\"street\": \"400 Robertson Alley Apt. 806\", \"city\": \"Florence\", \"country\": \"United States\"}", "specialty": "Accessoires Vintage", "lead_time_days": 25, "minimum_order": 814, "payment_terms": "Net 30", "quality_rating": 4.5, "established_date": "2014-03-19", "is_active": true, "vintage_era_focus": "Multi-\u00e9poque", "authentication_service": true, "certifications": "Authentifi\u00e9 Vestiaire"}
{"supplier_id": "SUP012", "name": "Vestiaire de Luxe", "contact_person": "Christopher Myers", "email": "contact@vestiairedeluxe.com", "phone": "5927302472", "address": "{\"street\": \"111 Williams Mall\", \"city\": \"Milan\", \"country\": \"United Kingdom\"}", "specialty": "Pi\u00e8ces Rares Collection", "lead_time_days": 28, "minimum_order": 646, "payment_terms": "Net 45", "quality_rating": 4.2, "established_date": "2021-05-16", "is_active": true, "vintage_era_focus": "1990s-2000s", "authentication_service": true, "certifications": "Certifi\u00e9 Maison"}
{"supplier_id": "SUP013", "name": "Maisons de Couture Parisiennes", "contact_person": "Amber Williams", "email": "contact@maisonsdecoutureparisiennes.com", "phone": "+1-941-550-8593", "address": "{\"street\": \"005 Chapman Flats Suite 355\", \"city\": \"New York\", \"country\": \"Belgium\"}", "specialty": "Pr\u00eat-\u00e0-Porter de Luxe", "lead_time_days": 22, "minimum_order": 1759, "payment_terms": "Virement imm\u00e9diat", "quality_rating": 4.7, "established_date": "2006-12-02", "is_active": true, "vintage_era_focus": "1950s-60s", "authentication_service": true, "certifications": "Authentifi\u00e9 Vestiaire"}
{"supplier_id": "SUP014", "name": "Vintage Couture House", "contact_person": "Duane Gates", "email": "contact@vintagecouturehouse.com", "phone": "2485405115", "address": "{\"street\": \"9963 Jacob Mills Apt. 596\", \"city\": \"Anvers\", \"country\": \"United States\"}", "specialty": "Haute Couture Vintage", "lead_time_days": 29, "minimum_order": 1734, "payment_terms": "Net 45", "quality_rating": 4.7, "established_date": "2015-05-13", "is_active": true, "vintage_era_focus": "Multi-\u00e9poque", "authentication_service": true, "certifications": "Authentifi\u00e9 Vestiaire"}
{"supplier_id": "SUP015", "name": "London Vintage Collective", "contact_person": "Shane Butler", "email": "contact@londonvintagecollective.com", "phone": "+1-423-829-4215x895", "address": "{\"street\": \"746 Burton Hollow\", \"city\": \"Anvers\", \"country\": \"France\"}", "specialty": "Pr\u00eat-\u00e0-Porter de Luxe", "lead_time_days": 10, "minimum_order": 896, "payment_terms": "Net 30", "quality_rating": 4.8, "established_date": "2016-07-18", "is_active": true, "vintage_era_focus": "1950s-60s", "authentication_service": true, "certifications": "Authentifi\u00e9 Vestiaire"}
{"supplier_id": "SUP016", "name": "Ateliers Vintage Milano", "contact_person": "Leon Jennings", "email": "contact@ateliersvintagemilano.com", "phone": "(568)974-7458x02424", "address": "{\"street\": \"5494 Carly Run\", \"city\": \"Florence\", \"country\": \"France\"}", "specialty": "Accessoires Vintage", "lead_time_days": 45, "minimum_order": 662, "payment_terms": "Net 45", "quality_rating": 4.5, "established_date": "2020-10-13", "is_active": true, "vintage_era_focus": "1970s-80s", "authentication_service": true, "certifications": "Expertise Ind\u00e9pendante"}
{"supplier_id": "SUP017", "name": "Ateliers Vintage Milano", "contact_person": "Shannon Vega", "email": "contact@ateliersvintagemilano.com", "phone": "001-776-337-6410", "address": "{\"street\": \"7896 Floyd Summit\", \"city\": \"Anvers\", \"country\": \"United Kingdom\"}", "specialty": "Haute Couture Vintage", "lead_time_days": 34, "minimum_order": 1630, "payment_terms": "Net 45", "quality_rating": 4.3, "established_date": "2017-03-07", "is_active": true, "vintage_era_focus": "Multi-\u00e9poque", "authentication_service": true, "certifications": "Expertise Ind\u00e9pendante"}
{"supplier_id": "SUP018", "name": "Maisons de Couture Parisiennes", "contact_person": "Patrick Morrison", "email": "contact@maisonsdecoutureparisiennes.com", "phone": "345.336.4295x908", "address": "{\"street\": \"4989 Anthony Burgs\", \"city\": \"New York\", \"country\": \"Japan\"}", "specialty": "Accessoires Vintage", "lead_time_days": 8, "minimum_order": 565, "payment_terms": "Net 30", "quality_rating": 4.2, "established_date": "2008-06-29", "is_active": true, "vintage_era_focus": "1970s-80s", "authentication_service": true, "certifications": "Expertise Ind\u00e9pendante"}
{"supplier_id": "SUP019", "name": "Archives Mode & Style", "contact_person": "Desiree Kennedy", "email": "contact@archivesmode&style.com", "phone": "001-486-299-7809x523", "address": "{\"street\": \"513 Johnson Ways\", \"city\": \"Milan\", \"country\": \"Italy\"}", "specialty": "Accessoires Vintage", "lead_time_days": 41, "minimum_order": 1927, "payment_terms": "Virement imm\u00e9diat", "quality_rating": 4.4, "established_date": "2011-11-08", "is_active": true, "vintage_era_focus": "1970s-80s", "authentication_service": true, "certifications": "Authentifi\u00e9 Vestiaire"}
{"supplier_id": "SUP020", "name": "Vintage Couture House", "contact_person": "Christine Thompson", "email": "contact@vintagecouturehouse.com", "phone": "798.506.6213", "address": "{\"street\": \"739 Sarah Burg\", \"city\": \"Florence\", \"country\": \"France\"}", "specialty": "Pi\u00e8ces Rares Collection", "lead_time_days": 14, "minimum_order": 1198, "payment_terms": "Net 45", "quality_rating": 4.5, "established_date": "2015-10-04", "is_active": true, "vintage_era_focus": "Multi-\u00e9poque", "authentication_service": true, "certifications": "Authentifi\u00e9 Vestiaire"}
{"supplier_id": "SUP021", "name": "Vintage Couture House", "contact_person": "Timothy Alvarez", "email": "contact@vintagecouturehouse.com", "phone": "+1-732-272-6323x549", "address": "{\"street\": \"24656 Chang Fields Suite 124\", \"city\": \"Florence\", \"country\": \"United Kingdom\"}", "specialty": "Pi\u00e8ces Rares Collection", "lead_time_days": 12, "minimum_order": 1987, "payment_terms": "Net 30", "quality_rating": 4.7, "established_date": "2021-10-25", "is_active": false, "vintage_era_focus": "1950s-60s", "authentication_service": true, "certifications": "Expertise Ind\u00e9pendante"}
{"supplier_id": "SUP022", "name": "London Vintage Collective", "contact_person": "Isaiah King", "email": "contact@londonvintagecollective.com", "phone": "+1-245-497-7553", "address": "{\"street\": \"14331 Caleb Estates\", \"city\": \"Tokyo\", \"country\": \"Belgium\"}", "specialty": "Accessoires Vintage", "lead_time_days": 42, "minimum_order": 1056, "payment_terms": "Net 30", "quality_rating": 4.7, "established_date": "2010-09-06", "is_active": true, "vintage_era_focus": "Multi-\u00e9poque", "authentication_service": false, "certifications": "Certifi\u00e9 Maison"}
{"supplier_id": "SUP023", "name": "Vintage Couture House", "contact_person": "Manuel Mcdonald", "email": "contact@vintagecouturehouse.com", "phone": "583-623-8568", "address": "{\"street\": \"5157 Thompson Plain Apt. 395\", \"city\": \"Milan\", \"country\": \"France\"}", "specialty": "Haute Couture Vintage", "lead_time_days": 8, "minimum_order": 341, "payment_terms": "Virement imm\u00e9diat", "quality_rating": 4.7, "established_date": "2008-09-19", "is_active": true, "vintage_era_focus": "Multi-\u00e9poque", "authentication_service": true, "certifications": "Expertise Ind\u00e9pendante"}
{"supplier_id": "SUP024", "name": "Collectors Europ\u00e9ens", "contact_person": "Mary Allison", "email": "contact@collectorseurop\u00e9ens.com", "phone": "357.318.8141", "address": "{\"street\": \"89925 Edward Road\", \"city\": \"Florence\", \"country\": \"Belgium\"}", "specialty": "Haute Couture Vintage", "lead_time_days": 34, "minimum_order": 1054, "payment_terms": "Net 30", "quality_rating": 4.9, "established_date": "2009-12-20", "is_active": true, "vintage_era_focus": "1950s-60s", "authentication_service": false, "certifications": "Authentifi\u00e9 Vestiaire"}
{"supplier_id": "SUP025", "name": "Maisons de Couture Parisiennes", "contact_person": "Linda Berry", "email": "contact@maisonsdecoutureparisiennes.com", "phone": "755.565.2946x40594", "address": "{\"street\": \"10407 Rios Fork Suite 093\", \"city\": \"Florence\", \"country\": \"United States\"}", "specialty": "Accessoires Vintage", "lead_time_days": 24, "minimum_order": 1764, "payment_terms": "Virement imm\u00e9diat", "quality_rating": 5.0, "established_date": "2017-09-18", "is_active": false, "vintage_era_focus": "1970s-80s", "authentication_service": true, "certifications": "Expertise Ind\u00e9pendante"}
